theodoretools/__init__.py
theodoretools/bot.py
theodoretools/fs.py
theodoretools/id.py
theodoretools/image.py
theodoretools/st.py
theodoretools/url.py
theodoretools-0.0.13.dist-info/METADATA
theodoretools-0.0.13.dist-info/WHEEL
theodoretools-0.0.13.dist-info/top_level.txt
theodoretools-0.0.13.dist-info/RECORD
